anaug/__init__.py
anaug/default/__init__.py
anaug/default/blur.py
anaug/default/crop.py
anaug/default/elastic_deformation.py
anaug/default/flip.py
anaug/default/intensity.py
anaug/default/noise.py
anaug/default/random_rotation.py
anaug/default/rotate.py
anaug/default/scale.py
anaug/medical/__init__.py
anaug/medical/random_lesion.py
anaug-0.1.4.dist-info/LICENSE
anaug-0.1.4.dist-info/METADATA
anaug-0.1.4.dist-info/WHEEL
anaug-0.1.4.dist-info/top_level.txt
anaug-0.1.4.dist-info/RECORD
