Metadata-Version: 2.1
Name: anaug
Version: 0.1.4
Summary: AnAugment: A Python library for diverse data augmentation.
Home-page: https://github.com/lunovian/an-augment
Author: lunovian
Author-email: nxan2911@gmail.com
Classifier: Programming Language :: Python :: 3
Classifier: License :: OSI Approved :: MIT License
Classifier: Operating System :: OS Independent
Requires-Python: >=3.8
License-File: LICENSE
Requires-Dist: numpy>=1.19.0
Requires-Dist: scipy>=1.5.0
Requires-Dist: opencv-python>=4.5.0
